[
  {
    "delegator": "matheusggr",
    "delegated_hp": 10238.009,
    "total_account_hp": 28978.22499578324,
    "last_user_post": "2023-07-11T21:49:54",
    "token_balance": 2428.449,
    "timestamp": "2025-03-08T15:25:27.000Z",
    "last_vote_date": null,
    "votes_month": 0,
    "in_curation_trail": true
  },
  {
    "delegator": "wiseagent",
    "delegated_hp": 7000.259,
    "total_account_hp": 76247.39262329672,
    "last_user_post": "2025-12-17T03:31:48",
    "token_balance": 200,
    "timestamp": "2025-12-17T00:20:27.000Z",
    "last_vote_date": "2025-12-17T00:04:00",
    "votes_month": 31,
    "in_curation_trail": false
  },
  {
    "delegator": "rimurutempest",
    "delegated_hp": 4502.778,
    "total_account_hp": 8866.402297568822,
    "last_user_post": "2025-12-17T09:33:24",
    "token_balance": 200.20995677,
    "timestamp": "2025-12-08T22:40:48.000Z",
    "last_vote_date": "2025-12-16T14:55:33",
    "votes_month": 25,
    "in_curation_trail": true
  },
  {
    "delegator": "tfranzini",
    "delegated_hp": 3120.027,
    "total_account_hp": 3959.574199440151,
    "last_user_post": "2025-11-05T00:59:06",
    "token_balance": 514.893,
    "timestamp": "2025-10-01T22:54:21.000Z",
    "last_vote_date": null,
    "votes_month": 0,
    "in_curation_trail": true
  },
  {
    "delegator": "mengao",
    "delegated_hp": 2018.845,
    "total_account_hp": 33162.70105158868,
    "last_user_post": "2025-12-16T05:24:15",
    "token_balance": 200.80588465,
    "timestamp": "2025-08-27T17:56:09.000Z",
    "last_vote_date": "2025-11-04T02:43:00",
    "votes_month": 0,
    "in_curation_trail": false
  },
  {
    "delegator": "shiftrox",
    "delegated_hp": 1200.511,
    "total_account_hp": 21249.29073905794,
    "last_user_post": "2025-12-17T05:09:21",
    "token_balance": 166.696,
    "timestamp": "2025-12-15T12:42:51.000Z",
    "last_vote_date": "2025-12-16T16:32:30",
    "votes_month": 24,
    "in_curation_trail": true
  },
  {
    "delegator": "michupa",
    "delegated_hp": 1070.78,
    "total_account_hp": 14230.656166742765,
    "last_user_post": "2025-12-17T11:43:06",
    "token_balance": 125.78072422,
    "timestamp": "2025-04-24T15:14:03.000Z",
    "last_vote_date": "2025-12-17T11:41:15",
    "votes_month": 28,
    "in_curation_trail": true
  },
  {
    "delegator": "gwajnberg",
    "delegated_hp": 1033.415,
    "total_account_hp": 17742.539042365876,
    "last_user_post": "2025-12-16T23:07:33",
    "token_balance": 91.40700001,
    "timestamp": "2025-11-05T21:52:12.000Z",
    "last_vote_date": "2025-12-16T22:51:51",
    "votes_month": 15,
    "in_curation_trail": false
  },
  {
    "delegator": "kaibagt",
    "delegated_hp": 1022.706,
    "total_account_hp": 6724.669164660866,
    "last_user_post": "2025-06-19T18:48:24",
    "token_balance": 100.61831016,
    "timestamp": "2025-04-12T16:32:00.000Z",
    "last_vote_date": null,
    "votes_month": 0,
    "in_curation_trail": true
  },
  {
    "delegator": "josiva",
    "delegated_hp": 1020.949,
    "total_account_hp": 4125.23001691546,
    "last_user_post": "2025-12-13T13:55:48",
    "token_balance": 66.225,
    "timestamp": "2025-05-30T00:49:18.000Z",
    "last_vote_date": "2025-12-13T13:49:03",
    "votes_month": 20,
    "in_curation_trail": true
  },
  {
    "delegator": "elderdark",
    "delegated_hp": 1018.68,
    "total_account_hp": 10604.474115538913,
    "last_user_post": "2025-12-14T02:37:21",
    "token_balance": 130.47239327,
    "timestamp": "2025-05-08T02:36:12.000Z",
    "last_vote_date": "2025-12-14T02:35:54",
    "votes_month": 9,
    "in_curation_trail": true
  },
  {
    "delegator": "blessskateshop",
    "delegated_hp": 1005.448,
    "total_account_hp": 2547.1859917599386,
    "last_user_post": "2025-12-15T22:14:09",
    "token_balance": 0,
    "timestamp": "2025-10-13T18:54:15.000Z",
    "last_vote_date": "2025-12-15T01:30:48",
    "votes_month": 10,
    "in_curation_trail": true
  },
  {
    "delegator": "pablito.saldo",
    "delegated_hp": 618.83,
    "total_account_hp": 3042.939353446175,
    "last_user_post": "2025-11-16T16:01:09",
    "token_balance": 51.915,
    "timestamp": "2024-12-02T00:41:12.000Z",
    "last_vote_date": "2025-10-26T00:17:45",
    "votes_month": 0,
    "in_curation_trail": true
  },
  {
    "delegator": "ricestrela",
    "delegated_hp": 610.418,
    "total_account_hp": 2082.136242428834,
    "last_user_post": "2025-12-14T15:35:15",
    "token_balance": 60.33272072,
    "timestamp": "2025-06-09T13:27:48.000Z",
    "last_vote_date": "2025-12-14T10:05:39",
    "votes_month": 6,
    "in_curation_trail": true
  },
  {
    "delegator": "xvlad",
    "delegated_hp": 538.055,
    "total_account_hp": 5813.9315753598385,
    "last_user_post": "2025-12-16T16:32:51",
    "token_balance": 0,
    "timestamp": "2023-07-08T22:07:09.000Z",
    "last_vote_date": null,
    "votes_month": 0,
    "in_curation_trail": false
  },
  {
    "delegator": "legalizabrazil",
    "delegated_hp": 537.021,
    "total_account_hp": 695.9992922148294,
    "last_user_post": "2024-11-24T13:51:27",
    "token_balance": 0,
    "timestamp": "2023-08-01T15:46:45.000Z",
    "last_vote_date": null,
    "votes_month": 0,
    "in_curation_trail": false
  },
  {
    "delegator": "lobaobh",
    "delegated_hp": 411.29,
    "total_account_hp": 686.8626003620304,
    "last_user_post": "2025-04-17T05:12:48",
    "token_balance": 57.858,
    "timestamp": "2025-01-11T17:39:45.000Z",
    "last_vote_date": null,
    "votes_month": 0,
    "in_curation_trail": true
  },
  {
    "delegator": "coyotelation",
    "delegated_hp": 408.863,
    "total_account_hp": 3515.73143464873,
    "last_user_post": "2025-12-17T04:43:24",
    "token_balance": 31.038,
    "timestamp": "2025-03-27T23:04:48.000Z",
    "last_vote_date": "2025-12-16T22:48:15",
    "votes_month": 21,
    "in_curation_trail": true
  },
  {
    "delegator": "crazyphantombr",
    "delegated_hp": 227.098,
    "total_account_hp": 14945.635006999873,
    "last_user_post": "2025-12-16T23:44:15",
    "token_balance": 297.70217843,
    "timestamp": "2025-12-11T12:09:39.000Z",
    "last_vote_date": "2025-12-16T23:44:42",
    "votes_month": 30,
    "in_curation_trail": true
  },
  {
    "delegator": "markitoelias",
    "delegated_hp": 226.518,
    "total_account_hp": 264.5953918843279,
    "last_user_post": "2025-11-29T10:35:30",
    "token_balance": 0,
    "timestamp": "2025-10-05T22:33:33.000Z",
    "last_vote_date": null,
    "votes_month": 0,
    "in_curation_trail": false
  },
  {
    "delegator": "nane-qts",
    "delegated_hp": 223.83,
    "total_account_hp": 628.5576678216715,
    "last_user_post": "2024-01-03T02:35:03",
    "token_balance": 15.889,
    "timestamp": "2025-05-23T14:15:15.000Z",
    "last_vote_date": null,
    "votes_month": 0,
    "in_curation_trail": true
  },
  {
    "delegator": "thomashnblum",
    "delegated_hp": 216.701,
    "total_account_hp": 599.1531068889351,
    "last_user_post": "2025-11-20T03:32:48",
    "token_balance": 26.461,
    "timestamp": "2023-04-15T20:46:24.000Z",
    "last_vote_date": "2025-11-20T03:32:15",
    "votes_month": 1,
    "in_curation_trail": true
  },
  {
    "delegator": "viniciotricolor",
    "delegated_hp": 215.447,
    "total_account_hp": 1044.9819162508131,
    "last_user_post": "2025-10-04T01:50:24",
    "token_balance": 27.123,
    "timestamp": "2023-06-26T04:36:27.000Z",
    "last_vote_date": null,
    "votes_month": 0,
    "in_curation_trail": false
  },
  {
    "delegator": "syel25",
    "delegated_hp": 213.079,
    "total_account_hp": 2123.5384383231776,
    "last_user_post": "2024-06-30T14:50:33",
    "token_balance": 0,
    "timestamp": "2023-11-06T16:28:12.000Z",
    "last_vote_date": null,
    "votes_month": 0,
    "in_curation_trail": true
  },
  {
    "delegator": "felipefabar",
    "delegated_hp": 210.89,
    "total_account_hp": 970.2991507037017,
    "last_user_post": "2024-06-24T13:13:27",
    "token_balance": 0,
    "timestamp": "2024-03-14T18:26:15.000Z",
    "last_vote_date": null,
    "votes_month": 0,
    "in_curation_trail": false
  },
  {
    "delegator": "wagnertamanaha",
    "delegated_hp": 200.868,
    "total_account_hp": 4063.9468705121494,
    "last_user_post": "2025-12-17T02:58:15",
    "token_balance": 12,
    "timestamp": "2025-10-25T21:59:12.000Z",
    "last_vote_date": "2025-12-17T02:58:45",
    "votes_month": 22,
    "in_curation_trail": false
  },
  {
    "delegator": "lincemarrom",
    "delegated_hp": 161.486,
    "total_account_hp": 740.7859572543548,
    "last_user_post": "2025-04-26T21:09:51",
    "token_balance": 26.76524818,
    "timestamp": "2023-07-03T15:50:48.000Z",
    "last_vote_date": null,
    "votes_month": 0,
    "in_curation_trail": true
  },
  {
    "delegator": "reibar",
    "delegated_hp": 155.152,
    "total_account_hp": 338.0787122608374,
    "last_user_post": "2025-10-15T23:50:03",
    "token_balance": 25.58,
    "timestamp": "2023-11-12T19:48:36.000Z",
    "last_vote_date": null,
    "votes_month": 0,
    "in_curation_trail": true
  },
  {
    "delegator": "sinvistaalsol",
    "delegated_hp": 154.91,
    "total_account_hp": 155.08166441843963,
    "last_user_post": "2020-12-27T19:35:18",
    "token_balance": 0,
    "timestamp": "2025-03-20T15:57:30.000Z",
    "last_vote_date": null,
    "votes_month": 0,
    "in_curation_trail": false
  },
  {
    "delegator": "jaopalas",
    "delegated_hp": 117.218,
    "total_account_hp": 432.07572318774123,
    "last_user_post": "2025-12-12T20:52:12",
    "token_balance": 3.261,
    "timestamp": "2025-04-30T15:51:42.000Z",
    "last_vote_date": null,
    "votes_month": 0,
    "in_curation_trail": true
  },
  {
    "delegator": "dreloop07",
    "delegated_hp": 108.975,
    "total_account_hp": 3126.949555546072,
    "last_user_post": "2025-12-05T14:27:36",
    "token_balance": 0,
    "timestamp": "2023-03-24T18:54:27.000Z",
    "last_vote_date": "2025-12-05T16:09:45",
    "votes_month": 6,
    "in_curation_trail": false
  },
  {
    "delegator": "underlock",
    "delegated_hp": 108.661,
    "total_account_hp": 9838.165304123042,
    "last_user_post": "2025-12-16T15:03:15",
    "token_balance": 25.31899872,
    "timestamp": "2023-03-10T21:57:33.000Z",
    "last_vote_date": "2025-12-16T15:03:42",
    "votes_month": 9,
    "in_curation_trail": true
  },
  {
    "delegator": "imagemvirtual",
    "delegated_hp": 108.574,
    "total_account_hp": 125.78675089758218,
    "last_user_post": "2019-05-30T15:46:30",
    "token_balance": 0,
    "timestamp": "2023-03-20T21:30:03.000Z",
    "last_vote_date": null,
    "votes_month": 0,
    "in_curation_trail": false
  },
  {
    "delegator": "giovanalrico",
    "delegated_hp": 108.574,
    "total_account_hp": 122.95627007255067,
    "last_user_post": "2019-04-23T00:46:03",
    "token_balance": 0,
    "timestamp": "2023-03-20T21:31:24.000Z",
    "last_vote_date": null,
    "votes_month": 0,
    "in_curation_trail": false
  },
  {
    "delegator": "mauriciolimax",
    "delegated_hp": 107.591,
    "total_account_hp": 1865.8746702001379,
    "last_user_post": "2025-09-27T15:39:54",
    "token_balance": 13.611,
    "timestamp": "2023-07-11T05:34:00.000Z",
    "last_vote_date": null,
    "votes_month": 0,
    "in_curation_trail": false
  },
  {
    "delegator": "hellene8",
    "delegated_hp": 101.78,
    "total_account_hp": 1072.3942220086817,
    "last_user_post": "2025-10-23T17:30:09",
    "token_balance": 5.839,
    "timestamp": "2025-05-18T19:45:27.000Z",
    "last_vote_date": null,
    "votes_month": 0,
    "in_curation_trail": false
  },
  {
    "delegator": "ogechukwu-martha",
    "delegated_hp": 101.49,
    "total_account_hp": 175.84155917945728,
    "last_user_post": "2025-11-26T09:23:36",
    "token_balance": 0,
    "timestamp": "2025-06-22T17:25:42.000Z",
    "last_vote_date": null,
    "votes_month": 0,
    "in_curation_trail": false
  },
  {
    "delegator": "eii",
    "delegated_hp": 100.447,
    "total_account_hp": 5178.106548859771,
    "last_user_post": "2025-12-17T08:25:09",
    "token_balance": 0,
    "timestamp": "2025-10-24T10:50:09.000Z",
    "last_vote_date": null,
    "votes_month": 0,
    "in_curation_trail": false
  },
  {
    "delegator": "d35tr0",
    "delegated_hp": 74.711,
    "total_account_hp": 167.31869600198195,
    "last_user_post": "2025-10-31T03:20:36",
    "token_balance": 0,
    "timestamp": "2023-10-16T00:16:06.000Z",
    "last_vote_date": null,
    "votes_month": 0,
    "in_curation_trail": true
  },
  {
    "delegator": "arthursiq5",
    "delegated_hp": 71.948,
    "total_account_hp": 254.84435351102957,
    "last_user_post": "2025-04-16T15:40:24",
    "token_balance": 13.915,
    "timestamp": "2023-08-03T20:49:00.000Z",
    "last_vote_date": null,
    "votes_month": 0,
    "in_curation_trail": true
  },
  {
    "delegator": "casagrande",
    "delegated_hp": 60.26,
    "total_account_hp": 66.6238439762934,
    "last_user_post": "2025-11-27T20:22:06",
    "token_balance": 5.03961038,
    "timestamp": "2025-10-25T21:41:48.000Z",
    "last_vote_date": "2025-11-26T02:09:45",
    "votes_month": 1,
    "in_curation_trail": true
  },
  {
    "delegator": "matheusggr.leo",
    "delegated_hp": 54.292,
    "total_account_hp": 134.26988258129506,
    "last_user_post": "2025-10-14T11:49:42",
    "token_balance": 0,
    "timestamp": "2023-03-20T01:27:27.000Z",
    "last_vote_date": null,
    "votes_month": 0,
    "in_curation_trail": true
  },
  {
    "delegator": "zombialien",
    "delegated_hp": 52.384,
    "total_account_hp": 316.5789129590567,
    "last_user_post": "2025-07-29T17:26:45",
    "token_balance": 0,
    "timestamp": "2024-06-03T20:55:39.000Z",
    "last_vote_date": null,
    "votes_month": 0,
    "in_curation_trail": false
  },
  {
    "delegator": "captainman",
    "delegated_hp": 52.273,
    "total_account_hp": 1179.9947068382846,
    "last_user_post": "2025-11-29T21:11:42",
    "token_balance": 0,
    "timestamp": "2024-06-28T21:57:57.000Z",
    "last_vote_date": null,
    "votes_month": 0,
    "in_curation_trail": true
  },
  {
    "delegator": "adncabrera",
    "delegated_hp": 51.35,
    "total_account_hp": 794.0411102673484,
    "last_user_post": "2025-12-15T02:20:48",
    "token_balance": 0.501,
    "timestamp": "2025-01-28T01:16:24.000Z",
    "last_vote_date": null,
    "votes_month": 0,
    "in_curation_trail": false
  },
  {
    "delegator": "grafvisionsp",
    "delegated_hp": 50.409,
    "total_account_hp": 1345.181219877186,
    "last_user_post": "2025-12-01T15:53:30",
    "token_balance": 0,
    "timestamp": "2025-09-11T12:45:39.000Z",
    "last_vote_date": "2025-11-27T23:16:12",
    "votes_month": 1,
    "in_curation_trail": false
  },
  {
    "delegator": "ladyaryastark",
    "delegated_hp": 50.118,
    "total_account_hp": 2331.2922321353994,
    "last_user_post": "2025-12-16T20:50:54",
    "token_balance": 0,
    "timestamp": "2025-11-15T22:00:00.000Z",
    "last_vote_date": "2025-10-24T15:23:51",
    "votes_month": 0,
    "in_curation_trail": false
  },
  {
    "delegator": "hive-br.leo",
    "delegated_hp": 44.134,
    "total_account_hp": 45.20910743723685,
    "last_user_post": "2023-07-15T22:43:27",
    "token_balance": 0,
    "timestamp": "2023-07-26T03:22:42.000Z",
    "last_vote_date": null,
    "votes_month": 0,
    "in_curation_trail": false
  },
  {
    "delegator": "ogepaul1986",
    "delegated_hp": 34.237,
    "total_account_hp": 39.26258832087286,
    "last_user_post": "2025-08-29T15:44:45",
    "token_balance": 0,
    "timestamp": "2025-10-16T21:18:42.000Z",
    "last_vote_date": null,
    "votes_month": 0,
    "in_curation_trail": false
  },
  {
    "delegator": "speedtuning",
    "delegated_hp": 32.102,
    "total_account_hp": 501.008116179642,
    "last_user_post": "2025-11-12T14:31:39",
    "token_balance": 0,
    "timestamp": "2023-09-14T22:47:57.000Z",
    "last_vote_date": null,
    "votes_month": 0,
    "in_curation_trail": false
  },
  {
    "delegator": "us3incanada",
    "delegated_hp": 30.033,
    "total_account_hp": 49.792218001955106,
    "last_user_post": "2025-08-05T00:44:33",
    "token_balance": 0,
    "timestamp": "2025-12-02T01:50:39.000Z",
    "last_vote_date": null,
    "votes_month": 0,
    "in_curation_trail": true
  },
  {
    "delegator": "boeltermc",
    "delegated_hp": 21.272,
    "total_account_hp": 3301.5919456558386,
    "last_user_post": "2025-07-28T01:37:42",
    "token_balance": 0,
    "timestamp": "2023-11-27T22:00:54.000Z",
    "last_vote_date": null,
    "votes_month": 0,
    "in_curation_trail": false
  },
  {
    "delegator": "keepkeybr",
    "delegated_hp": 13.889,
    "total_account_hp": 15.1311500214079,
    "last_user_post": "2023-08-20T19:24:33",
    "token_balance": 0,
    "timestamp": "2023-10-03T15:07:09.000Z",
    "last_vote_date": null,
    "votes_month": 0,
    "in_curation_trail": false
  },
  {
    "delegator": "name0",
    "delegated_hp": 10.456,
    "total_account_hp": 21843.16189448429,
    "last_user_post": "2025-11-19T00:01:27",
    "token_balance": 0,
    "timestamp": "2024-06-26T23:01:42.000Z",
    "last_vote_date": null,
    "votes_month": 0,
    "in_curation_trail": false
  },
  {
    "delegator": "sieghard1990",
    "delegated_hp": 10.314,
    "total_account_hp": 196.55298541875771,
    "last_user_post": "2025-10-22T09:40:48",
    "token_balance": 0,
    "timestamp": "2024-12-01T13:37:30.000Z",
    "last_vote_date": null,
    "votes_month": 0,
    "in_curation_trail": false
  },
  {
    "delegator": "v-36",
    "delegated_hp": 10.134,
    "total_account_hp": 96.35361478106867,
    "last_user_post": "2025-11-05T17:18:57",
    "token_balance": 0.614,
    "timestamp": "2025-07-10T10:59:54.000Z",
    "last_vote_date": null,
    "votes_month": 0,
    "in_curation_trail": false
  },
  {
    "delegator": "manopunkttt",
    "delegated_hp": 10.095,
    "total_account_hp": 98.21034791112967,
    "last_user_post": "2025-11-28T13:44:18",
    "token_balance": 0,
    "timestamp": "2025-08-26T22:39:30.000Z",
    "last_vote_date": "2025-11-28T13:14:33",
    "votes_month": 5,
    "in_curation_trail": false
  },
  {
    "delegator": "emviagem",
    "delegated_hp": 9.503,
    "total_account_hp": 9.949411499544642,
    "last_user_post": "2025-08-05T00:43:51",
    "token_balance": 0,
    "timestamp": "2025-04-10T10:02:57.000Z",
    "last_vote_date": null,
    "votes_month": 0,
    "in_curation_trail": true
  },
  {
    "delegator": "claytonlins",
    "delegated_hp": 6.105,
    "total_account_hp": 7.262257889370148,
    "last_user_post": "2024-11-04T01:35:42",
    "token_balance": 0,
    "timestamp": "2025-12-02T01:48:33.000Z",
    "last_vote_date": null,
    "votes_month": 0,
    "in_curation_trail": true
  },
  {
    "delegator": "jkatrina",
    "delegated_hp": 1.918,
    "total_account_hp": 20.078092460639617,
    "last_user_post": "2024-10-16T19:30:48",
    "token_balance": 0,
    "timestamp": "2025-12-02T01:51:27.000Z",
    "last_vote_date": null,
    "votes_month": 0,
    "in_curation_trail": true
  },
  {
    "delegator": "zulfrontado",
    "delegated_hp": 1.007,
    "total_account_hp": 2176.6655307101014,
    "last_user_post": "2025-12-17T00:16:15",
    "token_balance": 0,
    "timestamp": "2025-09-28T17:36:54.000Z",
    "last_vote_date": null,
    "votes_month": 0,
    "in_curation_trail": false
  },
  {
    "delegator": "abandeira",
    "delegated_hp": 0,
    "total_account_hp": 0,
    "last_user_post": "2024-02-04T14:45:45",
    "token_balance": 0,
    "timestamp": null,
    "last_vote_date": null,
    "votes_month": 0,
    "in_curation_trail": false
  },
  {
    "delegator": "aiuna",
    "delegated_hp": 0,
    "total_account_hp": 11.533639359766592,
    "last_user_post": "2025-06-25T23:55:15",
    "token_balance": 0,
    "timestamp": null,
    "last_vote_date": null,
    "votes_month": 0,
    "in_curation_trail": false
  },
  {
    "delegator": "aiyumi",
    "delegated_hp": 0,
    "total_account_hp": 1940.3323789797166,
    "last_user_post": "2022-01-27T20:53:30",
    "token_balance": 0,
    "timestamp": null,
    "last_vote_date": null,
    "votes_month": 0,
    "in_curation_trail": false
  },
  {
    "delegator": "ale-rio",
    "delegated_hp": 0,
    "total_account_hp": 7.2694544186195404,
    "last_user_post": "2025-05-15T00:59:48",
    "token_balance": 0,
    "timestamp": null,
    "last_vote_date": null,
    "votes_month": 0,
    "in_curation_trail": false
  },
  {
    "delegator": "alexandrefeliz",
    "delegated_hp": 0,
    "total_account_hp": 162.60819308207687,
    "last_user_post": "2025-12-05T21:39:12",
    "token_balance": 0,
    "timestamp": null,
    "last_vote_date": null,
    "votes_month": 0,
    "in_curation_trail": false
  },
  {
    "delegator": "alina97",
    "delegated_hp": 0,
    "total_account_hp": 578.8625039756438,
    "last_user_post": "2025-12-12T00:54:33",
    "token_balance": 0,
    "timestamp": null,
    "last_vote_date": null,
    "votes_month": 0,
    "in_curation_trail": false
  },
  {
    "delegator": "alinequeiroz",
    "delegated_hp": 0,
    "total_account_hp": 22.722019725616153,
    "last_user_post": "2024-12-17T23:12:03",
    "token_balance": 0,
    "timestamp": null,
    "last_vote_date": null,
    "votes_month": 0,
    "in_curation_trail": true
  },
  {
    "delegator": "alucardy",
    "delegated_hp": 0,
    "total_account_hp": 5.0680695478480295,
    "last_user_post": "2025-02-27T14:40:15",
    "token_balance": 0,
    "timestamp": null,
    "last_vote_date": null,
    "votes_month": 0,
    "in_curation_trail": false
  },
  {
    "delegator": "alyxmijaresda",
    "delegated_hp": 0,
    "total_account_hp": 0,
    "last_user_post": "2024-04-04T22:16:57",
    "token_balance": 0,
    "timestamp": null,
    "last_vote_date": null,
    "votes_month": 0,
    "in_curation_trail": false
  },
  {
    "delegator": "anacvv05",
    "delegated_hp": 0,
    "total_account_hp": 518.1402474824938,
    "last_user_post": "2025-05-22T11:01:00",
    "token_balance": 0,
    "timestamp": null,
    "last_vote_date": null,
    "votes_month": 0,
    "in_curation_trail": false
  },
  {
    "delegator": "anafenalli",
    "delegated_hp": 0,
    "total_account_hp": 0.22728671587523847,
    "last_user_post": "2024-05-01T02:14:36",
    "token_balance": 0,
    "timestamp": null,
    "last_vote_date": null,
    "votes_month": 0,
    "in_curation_trail": false
  },
  {
    "delegator": "anazn",
    "delegated_hp": 0,
    "total_account_hp": 7.390356639630203,
    "last_user_post": "2025-11-14T20:46:42",
    "token_balance": 0,
    "timestamp": null,
    "last_vote_date": null,
    "votes_month": 0,
    "in_curation_trail": false
  },
  {
    "delegator": "aphiel",
    "delegated_hp": 0,
    "total_account_hp": 54.571763768165745,
    "last_user_post": "2023-03-22T16:15:36",
    "token_balance": 0,
    "timestamp": null,
    "last_vote_date": null,
    "votes_month": 0,
    "in_curation_trail": false
  },
  {
    "delegator": "avedorada",
    "delegated_hp": 0,
    "total_account_hp": 0.8702755895782042,
    "last_user_post": "2024-10-16T19:07:24",
    "token_balance": 0,
    "timestamp": null,
    "last_vote_date": null,
    "votes_month": 0,
    "in_curation_trail": false
  },
  {
    "delegator": "avel692",
    "delegated_hp": 0,
    "total_account_hp": 173.6497873320073,
    "last_user_post": "2020-02-29T19:02:57",
    "token_balance": 0,
    "timestamp": null,
    "last_vote_date": null,
    "votes_month": 0,
    "in_curation_trail": false
  },
  {
    "delegator": "ayummi",
    "delegated_hp": 0,
    "total_account_hp": 15.736821187118164,
    "last_user_post": "2025-07-02T03:19:39",
    "token_balance": 0,
    "timestamp": null,
    "last_vote_date": null,
    "votes_month": 0,
    "in_curation_trail": true
  },
  {
    "delegator": "badge-182654",
    "delegated_hp": 0,
    "total_account_hp": 0,
    "last_user_post": "1970-01-01T00:00:00",
    "token_balance": 0,
    "timestamp": null,
    "last_vote_date": null,
    "votes_month": 0,
    "in_curation_trail": true
  },
  {
    "delegator": "barizon",
    "delegated_hp": 0,
    "total_account_hp": 62.52784148435036,
    "last_user_post": "2022-11-22T14:38:36",
    "token_balance": 0,
    "timestamp": null,
    "last_vote_date": null,
    "votes_month": 0,
    "in_curation_trail": false
  },
  {
    "delegator": "bastter",
    "delegated_hp": 0,
    "total_account_hp": 122.33139834584591,
    "last_user_post": "2021-02-21T00:08:51",
    "token_balance": 0,
    "timestamp": null,
    "last_vote_date": null,
    "votes_month": 0,
    "in_curation_trail": false
  },
  {
    "delegator": "bergmannadv",
    "delegated_hp": 0,
    "total_account_hp": 6.525186373387281,
    "last_user_post": "2024-09-25T00:01:03",
    "token_balance": 0,
    "timestamp": null,
    "last_vote_date": null,
    "votes_month": 0,
    "in_curation_trail": false
  },
  {
    "delegator": "bernardonassar",
    "delegated_hp": 0,
    "total_account_hp": 109.50351641668152,
    "last_user_post": "2024-05-29T23:24:06",
    "token_balance": 0,
    "timestamp": null,
    "last_vote_date": null,
    "votes_month": 0,
    "in_curation_trail": false
  },
  {
    "delegator": "boba1961",
    "delegated_hp": 0,
    "total_account_hp": 0.049904270411910305,
    "last_user_post": "2024-03-07T12:18:33",
    "token_balance": 0,
    "timestamp": null,
    "last_vote_date": null,
    "votes_month": 0,
    "in_curation_trail": false
  },
  {
    "delegator": "bodhi.rio",
    "delegated_hp": 0,
    "total_account_hp": 52.45493201950589,
    "last_user_post": "2024-05-24T01:48:51",
    "token_balance": 0,
    "timestamp": null,
    "last_vote_date": null,
    "votes_month": 0,
    "in_curation_trail": false
  },
  {
    "delegator": "borajogar",
    "delegated_hp": 0,
    "total_account_hp": 0,
    "last_user_post": "2025-01-14T06:26:21",
    "token_balance": 0,
    "timestamp": null,
    "last_vote_date": null,
    "votes_month": 0,
    "in_curation_trail": false
  },
  {
    "delegator": "brancarosamel",
    "delegated_hp": 0,
    "total_account_hp": 17.16397327334162,
    "last_user_post": "2022-11-28T00:46:33",
    "token_balance": 0,
    "timestamp": null,
    "last_vote_date": null,
    "votes_month": 0,
    "in_curation_trail": false
  },
  {
    "delegator": "brazilians",
    "delegated_hp": 0,
    "total_account_hp": 121.5288877368422,
    "last_user_post": "2024-02-12T03:46:48",
    "token_balance": 0,
    "timestamp": null,
    "last_vote_date": null,
    "votes_month": 0,
    "in_curation_trail": false
  },
  {
    "delegator": "caaio",
    "delegated_hp": 0,
    "total_account_hp": 29.060380032892393,
    "last_user_post": "2021-10-31T18:11:00",
    "token_balance": 0,
    "timestamp": null,
    "last_vote_date": null,
    "votes_month": 0,
    "in_curation_trail": false
  },
  {
    "delegator": "canellov",
    "delegated_hp": 0,
    "total_account_hp": 20.4539150053721,
    "last_user_post": "2024-09-05T17:31:45",
    "token_balance": 0,
    "timestamp": null,
    "last_vote_date": null,
    "votes_month": 0,
    "in_curation_trail": false
  },
  {
    "delegator": "capuah-iruet",
    "delegated_hp": 0,
    "total_account_hp": 0.14056738781718656,
    "last_user_post": "2024-11-02T04:37:51",
    "token_balance": 0,
    "timestamp": null,
    "last_vote_date": null,
    "votes_month": 0,
    "in_curation_trail": false
  },
  {
    "delegator": "carlosro",
    "delegated_hp": 0,
    "total_account_hp": 84.47528515872939,
    "last_user_post": "2024-02-29T09:49:21",
    "token_balance": 0,
    "timestamp": null,
    "last_vote_date": null,
    "votes_month": 0,
    "in_curation_trail": false
  },
  {
    "delegator": "carolramos",
    "delegated_hp": 0,
    "total_account_hp": 33.24411137048763,
    "last_user_post": "2025-04-21T22:12:36",
    "token_balance": 0,
    "timestamp": null,
    "last_vote_date": null,
    "votes_month": 0,
    "in_curation_trail": false
  },
  {
    "delegator": "christiantatsch",
    "delegated_hp": 0,
    "total_account_hp": 147.91884280782924,
    "last_user_post": "2024-05-28T20:38:12",
    "token_balance": 0,
    "timestamp": null,
    "last_vote_date": null,
    "votes_month": 0,
    "in_curation_trail": false
  },
  {
    "delegator": "cleateles1",
    "delegated_hp": 0,
    "total_account_hp": 7.341822589642413,
    "last_user_post": "2025-01-01T12:55:42",
    "token_balance": 0,
    "timestamp": null,
    "last_vote_date": null,
    "votes_month": 0,
    "in_curation_trail": false
  },
  {
    "delegator": "coiotes",
    "delegated_hp": 0,
    "total_account_hp": 11.772912766103497,
    "last_user_post": "2025-01-03T01:28:57",
    "token_balance": 0,
    "timestamp": null,
    "last_vote_date": null,
    "votes_month": 0,
    "in_curation_trail": true
  },
  {
    "delegator": "coyote.sports",
    "delegated_hp": 0,
    "total_account_hp": 8.981904940321321,
    "last_user_post": "2021-03-11T04:55:12",
    "token_balance": 0,
    "timestamp": null,
    "last_vote_date": null,
    "votes_month": 0,
    "in_curation_trail": false
  },
  {
    "delegator": "cril692003",
    "delegated_hp": 0,
    "total_account_hp": 9.141175463852116,
    "last_user_post": "2024-11-29T23:07:39",
    "token_balance": 0,
    "timestamp": null,
    "last_vote_date": null,
    "votes_month": 0,
    "in_curation_trail": false
  },
  {
    "delegator": "crisciacm",
    "delegated_hp": 0,
    "total_account_hp": 1020.8809588636725,
    "last_user_post": "2025-05-15T20:55:27",
    "token_balance": 0,
    "timestamp": null,
    "last_vote_date": null,
    "votes_month": 0,
    "in_curation_trail": false
  },
  {
    "delegator": "cryptoshaman007",
    "delegated_hp": 0,
    "total_account_hp": 5.208276652397138,
    "last_user_post": "2022-05-31T01:14:36",
    "token_balance": 0,
    "timestamp": null,
    "last_vote_date": null,
    "votes_month": 0,
    "in_curation_trail": false
  },
  {
    "delegator": "david0808",
    "delegated_hp": 0,
    "total_account_hp": 0,
    "last_user_post": "2024-09-04T19:31:18",
    "token_balance": 0,
    "timestamp": null,
    "last_vote_date": null,
    "votes_month": 0,
    "in_curation_trail": false
  },
  {
    "delegator": "deividluchi",
    "delegated_hp": 0,
    "total_account_hp": 156.9717484362386,
    "last_user_post": "2018-08-10T16:21:06",
    "token_balance": 0,
    "timestamp": null,
    "last_vote_date": null,
    "votes_month": 0,
    "in_curation_trail": false
  },
  {
    "delegator": "diegoguerra",
    "delegated_hp": 0,
    "total_account_hp": 180.09457410006618,
    "last_user_post": "2023-12-05T17:09:54",
    "token_balance": 0,
    "timestamp": null,
    "last_vote_date": null,
    "votes_month": 0,
    "in_curation_trail": false
  },
  {
    "delegator": "diogenesrm",
    "delegated_hp": 0,
    "total_account_hp": 0,
    "last_user_post": "2025-01-01T19:40:36",
    "token_balance": 0,
    "timestamp": null,
    "last_vote_date": null,
    "votes_month": 0,
    "in_curation_trail": false
  },
  {
    "delegator": "discernente",
    "delegated_hp": 0,
    "total_account_hp": 408.8358129245172,
    "last_user_post": "2025-11-26T19:04:51",
    "token_balance": 0,
    "timestamp": null,
    "last_vote_date": null,
    "votes_month": 0,
    "in_curation_trail": false
  },
  {
    "delegator": "disruptivas",
    "delegated_hp": 0,
    "total_account_hp": 179.37034306110232,
    "last_user_post": "2018-10-18T21:49:45",
    "token_balance": 0,
    "timestamp": null,
    "last_vote_date": null,
    "votes_month": 0,
    "in_curation_trail": false
  },
  {
    "delegator": "doblershiva",
    "delegated_hp": 0,
    "total_account_hp": 191.3621225993292,
    "last_user_post": "2025-09-17T03:08:51",
    "token_balance": 0,
    "timestamp": null,
    "last_vote_date": null,
    "votes_month": 0,
    "in_curation_trail": false
  },
  {
    "delegator": "dolandoteiro",
    "delegated_hp": 0,
    "total_account_hp": 6.21395090761526,
    "last_user_post": "2025-09-21T03:06:18",
    "token_balance": 0,
    "timestamp": null,
    "last_vote_date": null,
    "votes_month": 0,
    "in_curation_trail": false
  },
  {
    "delegator": "donamona",
    "delegated_hp": 0,
    "total_account_hp": 14.845328929169503,
    "last_user_post": "2024-06-18T23:51:30",
    "token_balance": 0,
    "timestamp": null,
    "last_vote_date": null,
    "votes_month": 0,
    "in_curation_trail": false
  },
  {
    "delegator": "dstampede",
    "delegated_hp": 0,
    "total_account_hp": 77.83400027374442,
    "last_user_post": "2025-12-16T19:59:03",
    "token_balance": 0,
    "timestamp": null,
    "last_vote_date": null,
    "votes_month": 0,
    "in_curation_trail": false
  },
  {
    "delegator": "dudutaulois",
    "delegated_hp": 0,
    "total_account_hp": 2068.7311342699163,
    "last_user_post": "2023-02-14T16:54:42",
    "token_balance": 0,
    "timestamp": null,
    "last_vote_date": null,
    "votes_month": 0,
    "in_curation_trail": false
  },
  {
    "delegator": "dunatos",
    "delegated_hp": 0,
    "total_account_hp": 25.056243219415,
    "last_user_post": "2020-08-26T20:20:54",
    "token_balance": 0,
    "timestamp": null,
    "last_vote_date": null,
    "votes_month": 0,
    "in_curation_trail": false
  },
  {
    "delegator": "edufecchio",
    "delegated_hp": 0,
    "total_account_hp": 3.165809280309053,
    "last_user_post": "2017-11-22T19:22:24",
    "token_balance": 0,
    "timestamp": null,
    "last_vote_date": null,
    "votes_month": 0,
    "in_curation_trail": false
  },
  {
    "delegator": "edvamfilho",
    "delegated_hp": 0,
    "total_account_hp": 2.091849498943157,
    "last_user_post": "2024-02-26T12:38:03",
    "token_balance": 0,
    "timestamp": null,
    "last_vote_date": null,
    "votes_month": 0,
    "in_curation_trail": false
  },
  {
    "delegator": "ehvinho",
    "delegated_hp": 0,
    "total_account_hp": 29.4278387651734,
    "last_user_post": "2025-02-15T14:19:57",
    "token_balance": 0,
    "timestamp": null,
    "last_vote_date": null,
    "votes_month": 0,
    "in_curation_trail": false
  },
  {
    "delegator": "eijibr",
    "delegated_hp": 0,
    "total_account_hp": 0.001538497577565166,
    "last_user_post": "2024-02-01T01:59:18",
    "token_balance": 0,
    "timestamp": null,
    "last_vote_date": null,
    "votes_month": 0,
    "in_curation_trail": false
  },
  {
    "delegator": "elcoachjesus",
    "delegated_hp": 0,
    "total_account_hp": 25.359892808583677,
    "last_user_post": "2024-11-11T00:50:36",
    "token_balance": 0,
    "timestamp": null,
    "last_vote_date": null,
    "votes_month": 0,
    "in_curation_trail": false
  },
  {
    "delegator": "emanueledornelas",
    "delegated_hp": 0,
    "total_account_hp": 277.51574533872,
    "last_user_post": "2025-05-26T22:58:03",
    "token_balance": 0,
    "timestamp": null,
    "last_vote_date": null,
    "votes_month": 0,
    "in_curation_trail": false
  },
  {
    "delegator": "endrius",
    "delegated_hp": 0,
    "total_account_hp": 6.699627141526135,
    "last_user_post": "2023-01-04T21:32:42",
    "token_balance": 0,
    "timestamp": null,
    "last_vote_date": null,
    "votes_month": 0,
    "in_curation_trail": false
  },
  {
    "delegator": "ericpso",
    "delegated_hp": 0,
    "total_account_hp": 191.9842467289192,
    "last_user_post": "2025-09-18T10:08:12",
    "token_balance": 0,
    "timestamp": null,
    "last_vote_date": null,
    "votes_month": 0,
    "in_curation_trail": false
  },
  {
    "delegator": "escadas",
    "delegated_hp": 0,
    "total_account_hp": 35.789770942372556,
    "last_user_post": "2023-09-07T02:47:03",
    "token_balance": 0,
    "timestamp": null,
    "last_vote_date": null,
    "votes_month": 0,
    "in_curation_trail": false
  },
  {
    "delegator": "estourefugiado",
    "delegated_hp": 0,
    "total_account_hp": 29.01145631267042,
    "last_user_post": "2018-06-26T21:46:27",
    "token_balance": 0,
    "timestamp": null,
    "last_vote_date": null,
    "votes_month": 0,
    "in_curation_trail": false
  },
  {
    "delegator": "eujotave",
    "delegated_hp": 0,
    "total_account_hp": 0.00041741908474036927,
    "last_user_post": "2024-11-09T02:47:54",
    "token_balance": 0,
    "timestamp": null,
    "last_vote_date": null,
    "votes_month": 0,
    "in_curation_trail": false
  },
  {
    "delegator": "f0rtunate",
    "delegated_hp": 0,
    "total_account_hp": 3.1687185577265935,
    "last_user_post": "2025-02-17T10:44:54",
    "token_balance": 0,
    "timestamp": null,
    "last_vote_date": null,
    "votes_month": 0,
    "in_curation_trail": false
  },
  {
    "delegator": "fabiocola",
    "delegated_hp": 0,
    "total_account_hp": 35.954350847724626,
    "last_user_post": "2020-03-01T00:33:57",
    "token_balance": 0,
    "timestamp": null,
    "last_vote_date": null,
    "votes_month": 0,
    "in_curation_trail": false
  },
  {
    "delegator": "fabiosoares",
    "delegated_hp": 0,
    "total_account_hp": 0,
    "last_user_post": "2024-04-11T00:07:00",
    "token_balance": 0,
    "timestamp": null,
    "last_vote_date": null,
    "votes_month": 0,
    "in_curation_trail": false
  },
  {
    "delegator": "felipefortes",
    "delegated_hp": 0,
    "total_account_hp": 19.232472885261497,
    "last_user_post": "2019-04-30T20:28:57",
    "token_balance": 0,
    "timestamp": null,
    "last_vote_date": null,
    "votes_month": 0,
    "in_curation_trail": false
  },
  {
    "delegator": "feliperochatv",
    "delegated_hp": 0,
    "total_account_hp": 124.5867081127522,
    "last_user_post": "2024-02-13T01:20:30",
    "token_balance": 0,
    "timestamp": null,
    "last_vote_date": null,
    "votes_month": 0,
    "in_curation_trail": false
  },
  {
    "delegator": "fernandosoder",
    "delegated_hp": 0,
    "total_account_hp": 1457.9023503565832,
    "last_user_post": "2025-12-13T15:32:51",
    "token_balance": 0,
    "timestamp": null,
    "last_vote_date": "2025-10-31T21:30:45",
    "votes_month": 0,
    "in_curation_trail": false
  },
  {
    "delegator": "fireguardian",
    "delegated_hp": 0,
    "total_account_hp": 109.04855302404383,
    "last_user_post": "2023-04-11T20:35:33",
    "token_balance": 0,
    "timestamp": null,
    "last_vote_date": null,
    "votes_month": 0,
    "in_curation_trail": true
  },
  {
    "delegator": "fireguardian.spt",
    "delegated_hp": 0,
    "total_account_hp": 0.4086364887159191,
    "last_user_post": "2021-06-15T16:55:33",
    "token_balance": 0,
    "timestamp": null,
    "last_vote_date": null,
    "votes_month": 0,
    "in_curation_trail": false
  },
  {
    "delegator": "floressenciarte",
    "delegated_hp": 0,
    "total_account_hp": 6.2226015848684275,
    "last_user_post": "2024-10-07T21:03:30",
    "token_balance": 0,
    "timestamp": null,
    "last_vote_date": null,
    "votes_month": 0,
    "in_curation_trail": false
  },
  {
    "delegator": "fmajuniorphoto",
    "delegated_hp": 0,
    "total_account_hp": 797.9629491804923,
    "last_user_post": "2025-04-17T11:01:54",
    "token_balance": 0,
    "timestamp": null,
    "last_vote_date": null,
    "votes_month": 0,
    "in_curation_trail": false
  },
  {
    "delegator": "frankrey11",
    "delegated_hp": 0,
    "total_account_hp": 143.14268523008445,
    "last_user_post": "2025-10-09T03:17:06",
    "token_balance": 0,
    "timestamp": null,
    "last_vote_date": null,
    "votes_month": 0,
    "in_curation_trail": false
  },
  {
    "delegator": "fredsilva007",
    "delegated_hp": 0,
    "total_account_hp": 1.8039922169076719,
    "last_user_post": "2021-05-13T15:40:57",
    "token_balance": 0,
    "timestamp": null,
    "last_vote_date": null,
    "votes_month": 0,
    "in_curation_trail": false
  },
  {
    "delegator": "g4tzbr",
    "delegated_hp": 0,
    "total_account_hp": 41.575025257817366,
    "last_user_post": "2024-10-01T20:04:39",
    "token_balance": 0,
    "timestamp": null,
    "last_vote_date": null,
    "votes_month": 0,
    "in_curation_trail": false
  },
  {
    "delegator": "gabrielmilego",
    "delegated_hp": 0,
    "total_account_hp": 0.0006177647520288267,
    "last_user_post": "1970-01-01T00:00:00",
    "token_balance": 0,
    "timestamp": null,
    "last_vote_date": null,
    "votes_month": 0,
    "in_curation_trail": false
  },
  {
    "delegator": "game3x3",
    "delegated_hp": 0,
    "total_account_hp": 15.14642778999957,
    "last_user_post": "2025-12-16T23:13:51",
    "token_balance": 0,
    "timestamp": null,
    "last_vote_date": null,
    "votes_month": 0,
    "in_curation_trail": true
  },
  {
    "delegator": "greengineer",
    "delegated_hp": 0,
    "total_account_hp": 62.14536495922667,
    "last_user_post": "2022-10-28T09:23:45",
    "token_balance": 0,
    "timestamp": null,
    "last_vote_date": null,
    "votes_month": 0,
    "in_curation_trail": false
  },
  {
    "delegator": "gtpacheko17",
    "delegated_hp": 0,
    "total_account_hp": 214.36845809175023,
    "last_user_post": "2025-12-16T20:48:57",
    "token_balance": 0,
    "timestamp": null,
    "last_vote_date": null,
    "votes_month": 0,
    "in_curation_trail": false
  },
  {
    "delegator": "handrehermann",
    "delegated_hp": 0,
    "total_account_hp": 104.97527041228577,
    "last_user_post": "2024-06-19T16:15:24",
    "token_balance": 0,
    "timestamp": null,
    "last_vote_date": null,
    "votes_month": 0,
    "in_curation_trail": false
  },
  {
    "delegator": "hevelyn.jeeh",
    "delegated_hp": 0,
    "total_account_hp": 5.1662531814108075,
    "last_user_post": "2024-06-03T18:38:03",
    "token_balance": 0,
    "timestamp": null,
    "last_vote_date": null,
    "votes_month": 0,
    "in_curation_trail": false
  },
  {
    "delegator": "hive-br",
    "delegated_hp": 0,
    "total_account_hp": 14191.933298729404,
    "last_user_post": "2025-12-01T21:26:42",
    "token_balance": 0,
    "timestamp": null,
    "last_vote_date": "2025-12-07T18:21:06",
    "votes_month": 3,
    "in_curation_trail": true
  },
  {
    "delegator": "hivebr.spt",
    "delegated_hp": 0,
    "total_account_hp": 28.0979641476057,
    "last_user_post": "2022-06-07T13:24:00",
    "token_balance": 0,
    "timestamp": null,
    "last_vote_date": null,
    "votes_month": 0,
    "in_curation_trail": false
  },
  {
    "delegator": "hive-br.voter",
    "delegated_hp": 0,
    "total_account_hp": 955.7036080276325,
    "last_user_post": "2025-12-17T11:41:15",
    "token_balance": 0,
    "timestamp": null,
    "last_vote_date": null,
    "votes_month": 0,
    "in_curation_trail": false
  },
  {
    "delegator": "hranhuk",
    "delegated_hp": 0,
    "total_account_hp": 201.91217428579168,
    "last_user_post": "2025-02-28T15:12:42",
    "token_balance": 0,
    "timestamp": null,
    "last_vote_date": null,
    "votes_month": 0,
    "in_curation_trail": false
  },
  {
    "delegator": "ismaelrd04",
    "delegated_hp": 0,
    "total_account_hp": 481.45973918528904,
    "last_user_post": "2025-12-15T23:39:54",
    "token_balance": 0,
    "timestamp": null,
    "last_vote_date": null,
    "votes_month": 0,
    "in_curation_trail": false
  },
  {
    "delegator": "iuriomagico",
    "delegated_hp": 0,
    "total_account_hp": 141.80603273245893,
    "last_user_post": "2024-07-17T09:00:51",
    "token_balance": 0,
    "timestamp": null,
    "last_vote_date": null,
    "votes_month": 0,
    "in_curation_trail": false
  },
  {
    "delegator": "j377e",
    "delegated_hp": 0,
    "total_account_hp": 18.82582916472728,
    "last_user_post": "2025-01-10T17:04:54",
    "token_balance": 0,
    "timestamp": null,
    "last_vote_date": null,
    "votes_month": 0,
    "in_curation_trail": false
  },
  {
    "delegator": "jacalf",
    "delegated_hp": 0,
    "total_account_hp": 31.396216454548213,
    "last_user_post": "2018-03-09T13:11:21",
    "token_balance": 0,
    "timestamp": null,
    "last_vote_date": null,
    "votes_month": 0,
    "in_curation_trail": false
  },
  {
    "delegator": "jaquevital",
    "delegated_hp": 0,
    "total_account_hp": 0,
    "last_user_post": "2024-08-23T18:36:33",
    "token_balance": 0,
    "timestamp": null,
    "last_vote_date": null,
    "votes_month": 0,
    "in_curation_trail": false
  },
  {
    "delegator": "jarmeson",
    "delegated_hp": 0,
    "total_account_hp": 43.937083321703646,
    "last_user_post": "2025-08-02T23:37:30",
    "token_balance": 0,
    "timestamp": null,
    "last_vote_date": null,
    "votes_month": 0,
    "in_curation_trail": true
  },
  {
    "delegator": "jeffparajiujitsu",
    "delegated_hp": 0,
    "total_account_hp": 8.10254789227108,
    "last_user_post": "2022-07-17T22:43:48",
    "token_balance": 0,
    "timestamp": null,
    "last_vote_date": null,
    "votes_month": 0,
    "in_curation_trail": false
  },
  {
    "delegator": "jklio123",
    "delegated_hp": 0,
    "total_account_hp": 132.5970194678977,
    "last_user_post": "2025-04-16T17:00:15",
    "token_balance": 0,
    "timestamp": null,
    "last_vote_date": null,
    "votes_month": 0,
    "in_curation_trail": false
  },
  {
    "delegator": "joaophelip",
    "delegated_hp": 0,
    "total_account_hp": 56.22497327338268,
    "last_user_post": "2024-07-18T18:49:03",
    "token_balance": 0,
    "timestamp": null,
    "last_vote_date": null,
    "votes_month": 0,
    "in_curation_trail": true
  },
  {
    "delegator": "joaoprobst",
    "delegated_hp": 0,
    "total_account_hp": 48.88190413374388,
    "last_user_post": "2018-12-13T17:38:57",
    "token_balance": 0,
    "timestamp": null,
    "last_vote_date": null,
    "votes_month": 0,
    "in_curation_trail": false
  },
  {
    "delegator": "jontv",
    "delegated_hp": 0,
    "total_account_hp": 124.20013294771641,
    "last_user_post": "2024-08-23T08:11:06",
    "token_balance": 0,
    "timestamp": null,
    "last_vote_date": null,
    "votes_month": 0,
    "in_curation_trail": false
  },
  {
    "delegator": "jose.music",
    "delegated_hp": 0,
    "total_account_hp": 15.649342252594055,
    "last_user_post": "2022-02-27T19:38:33",
    "token_balance": 0,
    "timestamp": null,
    "last_vote_date": null,
    "votes_month": 0,
    "in_curation_trail": false
  },
  {
    "delegator": "jsaez",
    "delegated_hp": 0,
    "total_account_hp": 81.5107916804268,
    "last_user_post": "2024-05-29T19:11:57",
    "token_balance": 0,
    "timestamp": null,
    "last_vote_date": null,
    "votes_month": 0,
    "in_curation_trail": false
  },
  {
    "delegator": "jsantana",
    "delegated_hp": 0,
    "total_account_hp": 15.044147565689283,
    "last_user_post": "2025-11-25T18:34:21",
    "token_balance": 0,
    "timestamp": null,
    "last_vote_date": null,
    "votes_month": 0,
    "in_curation_trail": true
  },
  {
    "delegator": "jucabala",
    "delegated_hp": 0,
    "total_account_hp": 217.10311532128634,
    "last_user_post": "2025-12-06T15:43:03",
    "token_balance": 0,
    "timestamp": null,
    "last_vote_date": null,
    "votes_month": 0,
    "in_curation_trail": false
  },
  {
    "delegator": "juliasantos",
    "delegated_hp": 0,
    "total_account_hp": 8.146029171178608,
    "last_user_post": "2024-08-08T13:10:24",
    "token_balance": 0,
    "timestamp": null,
    "last_vote_date": null,
    "votes_month": 0,
    "in_curation_trail": false
  },
  {
    "delegator": "jullyette",
    "delegated_hp": 0,
    "total_account_hp": 5.112387708009027,
    "last_user_post": "2024-01-10T19:19:24",
    "token_balance": 0,
    "timestamp": null,
    "last_vote_date": null,
    "votes_month": 0,
    "in_curation_trail": false
  },
  {
    "delegator": "kat.eli",
    "delegated_hp": 0,
    "total_account_hp": 120.54464410466859,
    "last_user_post": "2024-09-05T13:59:39",
    "token_balance": 0,
    "timestamp": null,
    "last_vote_date": null,
    "votes_month": 0,
    "in_curation_trail": false
  },
  {
    "delegator": "kaveira",
    "delegated_hp": 0,
    "total_account_hp": 55.778206619395164,
    "last_user_post": "2025-02-06T22:57:51",
    "token_balance": 0,
    "timestamp": null,
    "last_vote_date": null,
    "votes_month": 0,
    "in_curation_trail": true
  },
  {
    "delegator": "kelday666",
    "delegated_hp": 0,
    "total_account_hp": 323.14178332891237,
    "last_user_post": "2023-11-04T16:43:36",
    "token_balance": 0,
    "timestamp": null,
    "last_vote_date": null,
    "votes_month": 0,
    "in_curation_trail": false
  },
  {
    "delegator": "kevbest",
    "delegated_hp": 0,
    "total_account_hp": 4.448435356943175,
    "last_user_post": "2024-12-18T01:17:21",
    "token_balance": 0,
    "timestamp": null,
    "last_vote_date": null,
    "votes_month": 0,
    "in_curation_trail": true
  },
  {
    "delegator": "kingforceblack",
    "delegated_hp": 0,
    "total_account_hp": 1.0924985090163666,
    "last_user_post": "2025-12-13T22:13:54",
    "token_balance": 0,
    "timestamp": null,
    "last_vote_date": null,
    "votes_month": 0,
    "in_curation_trail": false
  },
  {
    "delegator": "kojiri",
    "delegated_hp": 0,
    "total_account_hp": 608.0216390008736,
    "last_user_post": "2024-06-13T13:11:27",
    "token_balance": 0,
    "timestamp": null,
    "last_vote_date": null,
    "votes_month": 0,
    "in_curation_trail": false
  },
  {
    "delegator": "laribf",
    "delegated_hp": 0,
    "total_account_hp": 2.086141991195447,
    "last_user_post": "2024-07-31T21:22:45",
    "token_balance": 0,
    "timestamp": null,
    "last_vote_date": null,
    "votes_month": 0,
    "in_curation_trail": false
  },
  {
    "delegator": "laurasoares",
    "delegated_hp": 0,
    "total_account_hp": 29.232571105308903,
    "last_user_post": "2019-05-29T20:38:18",
    "token_balance": 0,
    "timestamp": null,
    "last_vote_date": null,
    "votes_month": 0,
    "in_curation_trail": false
  },
  {
    "delegator": "leo.marques",
    "delegated_hp": 0,
    "total_account_hp": 0,
    "last_user_post": "2024-08-09T13:48:51",
    "token_balance": 0,
    "timestamp": null,
    "last_vote_date": null,
    "votes_month": 0,
    "in_curation_trail": false
  },
  {
    "delegator": "lesulzbacher",
    "delegated_hp": 0,
    "total_account_hp": 407.88486835385106,
    "last_user_post": "2025-02-25T01:27:57",
    "token_balance": 0,
    "timestamp": null,
    "last_vote_date": null,
    "votes_month": 0,
    "in_curation_trail": false
  },
  {
    "delegator": "lipe100dedos",
    "delegated_hp": 0,
    "total_account_hp": 5.083123491116112,
    "last_user_post": "2025-03-18T01:44:00",
    "token_balance": 0,
    "timestamp": null,
    "last_vote_date": null,
    "votes_month": 0,
    "in_curation_trail": false
  },
  {
    "delegator": "liquideity",
    "delegated_hp": 0,
    "total_account_hp": 5.9919881457362365,
    "last_user_post": "2024-03-17T22:44:33",
    "token_balance": 0,
    "timestamp": null,
    "last_vote_date": null,
    "votes_month": 0,
    "in_curation_trail": false
  },
  {
    "delegator": "litekoiner",
    "delegated_hp": 0,
    "total_account_hp": 19.594489555657944,
    "last_user_post": "2024-03-29T01:18:15",
    "token_balance": 0,
    "timestamp": null,
    "last_vote_date": null,
    "votes_month": 0,
    "in_curation_trail": false
  },
  {
    "delegator": "luanaecard",
    "delegated_hp": 0,
    "total_account_hp": 0.1165876514433022,
    "last_user_post": "2024-12-14T14:26:33",
    "token_balance": 0,
    "timestamp": null,
    "last_vote_date": null,
    "votes_month": 0,
    "in_curation_trail": false
  },
  {
    "delegator": "ludgero",
    "delegated_hp": 0,
    "total_account_hp": 0.3234922920690964,
    "last_user_post": "2024-11-06T19:03:24",
    "token_balance": 0,
    "timestamp": null,
    "last_vote_date": null,
    "votes_month": 0,
    "in_curation_trail": false
  },
  {
    "delegator": "luidimarg",
    "delegated_hp": 0,
    "total_account_hp": 337.47869359891905,
    "last_user_post": "2022-07-17T16:41:36",
    "token_balance": 0,
    "timestamp": null,
    "last_vote_date": null,
    "votes_month": 0,
    "in_curation_trail": false
  },
  {
    "delegator": "luizeba",
    "delegated_hp": 0,
    "total_account_hp": 157.4312931534615,
    "last_user_post": "2025-08-15T18:09:54",
    "token_balance": 0,
    "timestamp": null,
    "last_vote_date": null,
    "votes_month": 0,
    "in_curation_trail": true
  },
  {
    "delegator": "luizhadad",
    "delegated_hp": 0,
    "total_account_hp": 363.9086994995202,
    "last_user_post": "2025-02-14T02:03:48",
    "token_balance": 0,
    "timestamp": null,
    "last_vote_date": null,
    "votes_month": 0,
    "in_curation_trail": false
  },
  {
    "delegator": "maismau",
    "delegated_hp": 0,
    "total_account_hp": 62.93908172004248,
    "last_user_post": "2022-11-08T19:29:42",
    "token_balance": 0,
    "timestamp": null,
    "last_vote_date": null,
    "votes_month": 0,
    "in_curation_trail": false
  },
  {
    "delegator": "marianaemilia",
    "delegated_hp": 0,
    "total_account_hp": 259.3688723373694,
    "last_user_post": "2025-09-02T11:59:12",
    "token_balance": 0,
    "timestamp": null,
    "last_vote_date": null,
    "votes_month": 0,
    "in_curation_trail": false
  },
  {
    "delegator": "marzukiali",
    "delegated_hp": 0,
    "total_account_hp": 0,
    "last_user_post": "2024-10-05T02:24:27",
    "token_balance": 0,
    "timestamp": null,
    "last_vote_date": null,
    "votes_month": 0,
    "in_curation_trail": false
  },
  {
    "delegator": "matheusluciano",
    "delegated_hp": 0,
    "total_account_hp": 0,
    "last_user_post": "1970-01-01T00:00:00",
    "token_balance": 0,
    "timestamp": null,
    "last_vote_date": null,
    "votes_month": 0,
    "in_curation_trail": false
  },
  {
    "delegator": "mathfb",
    "delegated_hp": 0,
    "total_account_hp": 5.2474413788513266,
    "last_user_post": "2023-06-22T15:00:27",
    "token_balance": 0,
    "timestamp": null,
    "last_vote_date": null,
    "votes_month": 0,
    "in_curation_trail": false
  },
  {
    "delegator": "megamariano",
    "delegated_hp": 0,
    "total_account_hp": 59.85335089658114,
    "last_user_post": "2024-06-21T01:43:54",
    "token_balance": 0,
    "timestamp": null,
    "last_vote_date": null,
    "votes_month": 0,
    "in_curation_trail": false
  },
  {
    "delegator": "meinickenutri",
    "delegated_hp": 0,
    "total_account_hp": 0.5095537796016462,
    "last_user_post": "2024-04-27T05:24:51",
    "token_balance": 0,
    "timestamp": null,
    "last_vote_date": null,
    "votes_month": 0,
    "in_curation_trail": false
  },
  {
    "delegator": "micloop",
    "delegated_hp": 0,
    "total_account_hp": 136.62132254128468,
    "last_user_post": "2019-07-09T11:30:09",
    "token_balance": 0,
    "timestamp": null,
    "last_vote_date": null,
    "votes_month": 0,
    "in_curation_trail": false
  },
  {
    "delegator": "milery",
    "delegated_hp": 0,
    "total_account_hp": 0,
    "last_user_post": "2024-12-17T18:30:18",
    "token_balance": 0,
    "timestamp": null,
    "last_vote_date": null,
    "votes_month": 0,
    "in_curation_trail": false
  },
  {
    "delegator": "mrprofessor",
    "delegated_hp": 0,
    "total_account_hp": 1.7430402683807302,
    "last_user_post": "2025-04-22T21:42:48",
    "token_balance": 0,
    "timestamp": null,
    "last_vote_date": null,
    "votes_month": 0,
    "in_curation_trail": false
  },
  {
    "delegator": "mrprofessordaily",
    "delegated_hp": 0,
    "total_account_hp": 0.0009068325576796847,
    "last_user_post": "2024-02-15T00:28:24",
    "token_balance": 0,
    "timestamp": null,
    "last_vote_date": null,
    "votes_month": 0,
    "in_curation_trail": false
  },
  {
    "delegator": "naoebemumcanal",
    "delegated_hp": 0,
    "total_account_hp": 12.222524851133874,
    "last_user_post": "2024-07-02T22:21:09",
    "token_balance": 0,
    "timestamp": null,
    "last_vote_date": null,
    "votes_month": 0,
    "in_curation_trail": false
  },
  {
    "delegator": "nascimentoab",
    "delegated_hp": 0,
    "total_account_hp": 856.659313348215,
    "last_user_post": "2025-06-27T21:49:06",
    "token_balance": 0,
    "timestamp": null,
    "last_vote_date": null,
    "votes_month": 0,
    "in_curation_trail": false
  },
  {
    "delegator": "nascimentocb",
    "delegated_hp": 0,
    "total_account_hp": 49.417060830696094,
    "last_user_post": "2021-03-20T15:24:45",
    "token_balance": 0,
    "timestamp": null,
    "last_vote_date": null,
    "votes_month": 0,
    "in_curation_trail": false
  },
  {
    "delegator": "nathylieth",
    "delegated_hp": 0,
    "total_account_hp": 134.66539724573317,
    "last_user_post": "2023-11-23T20:35:36",
    "token_balance": 0,
    "timestamp": null,
    "last_vote_date": null,
    "votes_month": 0,
    "in_curation_trail": false
  },
  {
    "delegator": "nayha23",
    "delegated_hp": 0,
    "total_account_hp": 46.616499727813675,
    "last_user_post": "2022-02-10T02:13:09",
    "token_balance": 0,
    "timestamp": null,
    "last_vote_date": null,
    "votes_month": 0,
    "in_curation_trail": false
  },
  {
    "delegator": "nichollasrdo",
    "delegated_hp": 0,
    "total_account_hp": 10.853791589672454,
    "last_user_post": "2024-06-21T02:57:03",
    "token_balance": 0,
    "timestamp": null,
    "last_vote_date": null,
    "votes_month": 0,
    "in_curation_trail": false
  },
  {
    "delegator": "norseland",
    "delegated_hp": 0,
    "total_account_hp": 162.85978641985952,
    "last_user_post": "2023-06-07T11:04:21",
    "token_balance": 0,
    "timestamp": null,
    "last_vote_date": null,
    "votes_month": 0,
    "in_curation_trail": false
  },
  {
    "delegator": "officialjag",
    "delegated_hp": 0,
    "total_account_hp": 0,
    "last_user_post": "2024-08-04T20:53:57",
    "token_balance": 0,
    "timestamp": null,
    "last_vote_date": null,
    "votes_month": 0,
    "in_curation_trail": false
  },
  {
    "delegator": "oficialversatil",
    "delegated_hp": 0,
    "total_account_hp": 7.449594635877501,
    "last_user_post": "2024-09-08T16:17:54",
    "token_balance": 0,
    "timestamp": null,
    "last_vote_date": null,
    "votes_month": 0,
    "in_curation_trail": false
  },
  {
    "delegator": "orozcorobetson",
    "delegated_hp": 0,
    "total_account_hp": 2.6116651385207033,
    "last_user_post": "2024-06-22T03:36:51",
    "token_balance": 0,
    "timestamp": null,
    "last_vote_date": null,
    "votes_month": 0,
    "in_curation_trail": false
  },
  {
    "delegator": "papoprodutivo",
    "delegated_hp": 0,
    "total_account_hp": 0,
    "last_user_post": "2024-12-30T18:11:06",
    "token_balance": 0,
    "timestamp": null,
    "last_vote_date": null,
    "votes_month": 0,
    "in_curation_trail": false
  },
  {
    "delegator": "paradaleticia",
    "delegated_hp": 0,
    "total_account_hp": 617.9420265787813,
    "last_user_post": "2024-08-12T17:01:33",
    "token_balance": 0,
    "timestamp": null,
    "last_vote_date": null,
    "votes_month": 0,
    "in_curation_trail": false
  },
  {
    "delegator": "pataty69",
    "delegated_hp": 0,
    "total_account_hp": 209.4073474287241,
    "last_user_post": "2025-02-16T12:52:45",
    "token_balance": 18.66,
    "timestamp": null,
    "last_vote_date": null,
    "votes_month": 0,
    "in_curation_trail": false
  },
  {
    "delegator": "pedagogia",
    "delegated_hp": 0,
    "total_account_hp": 0.017408897339830354,
    "last_user_post": "2024-06-21T00:02:39",
    "token_balance": 0,
    "timestamp": null,
    "last_vote_date": null,
    "votes_month": 0,
    "in_curation_trail": false
  },
  {
    "delegator": "pedrocanella",
    "delegated_hp": 0,
    "total_account_hp": 28.840680669383843,
    "last_user_post": "2021-04-05T11:52:57",
    "token_balance": 0,
    "timestamp": null,
    "last_vote_date": null,
    "votes_month": 0,
    "in_curation_trail": false
  },
  {
    "delegator": "perfilbrasil",
    "delegated_hp": 0,
    "total_account_hp": 634.9193647280204,
    "last_user_post": "2025-11-19T12:27:45",
    "token_balance": 0,
    "timestamp": null,
    "last_vote_date": null,
    "votes_month": 0,
    "in_curation_trail": false
  },
  {
    "delegator": "phgnomo",
    "delegated_hp": 0,
    "total_account_hp": 1568.836392576109,
    "last_user_post": "2023-01-16T18:13:18",
    "token_balance": 0,
    "timestamp": null,
    "last_vote_date": null,
    "votes_month": 0,
    "in_curation_trail": false
  },
  {
    "delegator": "phsaeta",
    "delegated_hp": 0,
    "total_account_hp": 0,
    "last_user_post": "2024-09-27T00:24:36",
    "token_balance": 0,
    "timestamp": null,
    "last_vote_date": null,
    "votes_month": 0,
    "in_curation_trail": false
  },
  {
    "delegator": "pirulito.zoado",
    "delegated_hp": 0,
    "total_account_hp": 5.758399443654253,
    "last_user_post": "2024-09-03T13:01:39",
    "token_balance": 0,
    "timestamp": null,
    "last_vote_date": null,
    "votes_month": 0,
    "in_curation_trail": false
  },
  {
    "delegator": "pythomaster",
    "delegated_hp": 0,
    "total_account_hp": 57.3239981089568,
    "last_user_post": "2024-03-11T20:10:09",
    "token_balance": 0,
    "timestamp": null,
    "last_vote_date": null,
    "votes_month": 0,
    "in_curation_trail": false
  },
  {
    "delegator": "qyses",
    "delegated_hp": 0,
    "total_account_hp": 120.31923307427708,
    "last_user_post": "2022-09-07T22:59:06",
    "token_balance": 0,
    "timestamp": null,
    "last_vote_date": null,
    "votes_month": 0,
    "in_curation_trail": false
  },
  {
    "delegator": "raistling",
    "delegated_hp": 0,
    "total_account_hp": 273.95571662895816,
    "last_user_post": "2025-04-05T06:12:51",
    "token_balance": 0,
    "timestamp": null,
    "last_vote_date": null,
    "votes_month": 0,
    "in_curation_trail": false
  },
  {
    "delegator": "rdabrasil",
    "delegated_hp": 0,
    "total_account_hp": 1.428212251018425,
    "last_user_post": "2025-02-16T21:31:00",
    "token_balance": 0,
    "timestamp": null,
    "last_vote_date": null,
    "votes_month": 0,
    "in_curation_trail": false
  },
  {
    "delegator": "reas63",
    "delegated_hp": 0,
    "total_account_hp": 0.4381897497001173,
    "last_user_post": "2025-05-18T00:54:51",
    "token_balance": 0,
    "timestamp": null,
    "last_vote_date": null,
    "votes_month": 0,
    "in_curation_trail": false
  },
  {
    "delegator": "renatacristiane",
    "delegated_hp": 0,
    "total_account_hp": 1.3827539326356086,
    "last_user_post": "2025-02-01T19:58:03",
    "token_balance": 0,
    "timestamp": null,
    "last_vote_date": null,
    "votes_month": 0,
    "in_curation_trail": false
  },
  {
    "delegator": "rhommar",
    "delegated_hp": 0,
    "total_account_hp": 41.1875568145052,
    "last_user_post": "2025-01-31T20:49:51",
    "token_balance": 0,
    "timestamp": null,
    "last_vote_date": null,
    "votes_month": 0,
    "in_curation_trail": false
  },
  {
    "delegator": "rimasx",
    "delegated_hp": 0,
    "total_account_hp": 5.231192376167877,
    "last_user_post": "2024-06-21T00:17:06",
    "token_balance": 0,
    "timestamp": null,
    "last_vote_date": null,
    "votes_month": 0,
    "in_curation_trail": false
  },
  {
    "delegator": "robspiercer",
    "delegated_hp": 0,
    "total_account_hp": 0,
    "last_user_post": "2025-01-19T13:55:36",
    "token_balance": 0,
    "timestamp": null,
    "last_vote_date": null,
    "votes_month": 0,
    "in_curation_trail": false
  },
  {
    "delegator": "rodrigojmelo",
    "delegated_hp": 0,
    "total_account_hp": 0.057394305702083585,
    "last_user_post": "2020-02-13T18:34:18",
    "token_balance": 0,
    "timestamp": null,
    "last_vote_date": null,
    "votes_month": 0,
    "in_curation_trail": false
  },
  {
    "delegator": "rounan.soares",
    "delegated_hp": 0,
    "total_account_hp": 0,
    "last_user_post": "2025-08-30T05:31:51",
    "token_balance": 0,
    "timestamp": null,
    "last_vote_date": null,
    "votes_month": 0,
    "in_curation_trail": false
  },
  {
    "delegator": "rphspinheiro",
    "delegated_hp": 0,
    "total_account_hp": 6.427399560244592,
    "last_user_post": "2023-01-17T19:20:03",
    "token_balance": 0,
    "timestamp": null,
    "last_vote_date": null,
    "votes_month": 0,
    "in_curation_trail": false
  },
  {
    "delegator": "sandranunes",
    "delegated_hp": 0,
    "total_account_hp": 3.5266785194695123,
    "last_user_post": "2024-02-07T06:21:12",
    "token_balance": 0,
    "timestamp": null,
    "last_vote_date": null,
    "votes_month": 0,
    "in_curation_trail": false
  },
  {
    "delegator": "santana37",
    "delegated_hp": 0,
    "total_account_hp": 35.14507854584727,
    "last_user_post": "2024-03-16T02:33:39",
    "token_balance": 0,
    "timestamp": null,
    "last_vote_date": null,
    "votes_month": 0,
    "in_curation_trail": false
  },
  {
    "delegator": "santinhos",
    "delegated_hp": 0,
    "total_account_hp": 54.985867975887935,
    "last_user_post": "2018-02-26T20:56:00",
    "token_balance": 0,
    "timestamp": null,
    "last_vote_date": null,
    "votes_month": 0,
    "in_curation_trail": false
  },
  {
    "delegator": "seabet",
    "delegated_hp": 0,
    "total_account_hp": 0,
    "last_user_post": "2024-04-13T07:59:00",
    "token_balance": 0,
    "timestamp": null,
    "last_vote_date": null,
    "votes_month": 0,
    "in_curation_trail": false
  },
  {
    "delegator": "selhomarlopes",
    "delegated_hp": 0,
    "total_account_hp": 12.729095928770986,
    "last_user_post": "2025-09-26T01:09:15",
    "token_balance": 0,
    "timestamp": null,
    "last_vote_date": null,
    "votes_month": 0,
    "in_curation_trail": false
  },
  {
    "delegator": "silviamaria",
    "delegated_hp": 0,
    "total_account_hp": 488.75454017563254,
    "last_user_post": "2025-12-16T11:18:42",
    "token_balance": 0,
    "timestamp": null,
    "last_vote_date": null,
    "votes_month": 0,
    "in_curation_trail": false
  },
  {
    "delegator": "sintropia",
    "delegated_hp": 0,
    "total_account_hp": 0.3123302973242496,
    "last_user_post": "2025-07-08T17:04:00",
    "token_balance": 0,
    "timestamp": null,
    "last_vote_date": null,
    "votes_month": 0,
    "in_curation_trail": false
  },
  {
    "delegator": "sistemabusiness",
    "delegated_hp": 0,
    "total_account_hp": 77.66439043911271,
    "last_user_post": "2025-12-12T15:01:45",
    "token_balance": 0,
    "timestamp": null,
    "last_vote_date": null,
    "votes_month": 0,
    "in_curation_trail": false
  },
  {
    "delegator": "skaters",
    "delegated_hp": 0,
    "total_account_hp": 353.95787551264334,
    "last_user_post": "2025-12-15T20:18:12",
    "token_balance": 0,
    "timestamp": null,
    "last_vote_date": null,
    "votes_month": 0,
    "in_curation_trail": true
  },
  {
    "delegator": "sktbr",
    "delegated_hp": 0,
    "total_account_hp": 397.36839918369327,
    "last_user_post": "2024-01-30T21:20:51",
    "token_balance": 0,
    "timestamp": null,
    "last_vote_date": null,
    "votes_month": 0,
    "in_curation_trail": false
  },
  {
    "delegator": "sousafrc",
    "delegated_hp": 0,
    "total_account_hp": 55.40517404752839,
    "last_user_post": "2024-06-23T13:14:42",
    "token_balance": 0,
    "timestamp": null,
    "last_vote_date": null,
    "votes_month": 0,
    "in_curation_trail": false
  },
  {
    "delegator": "splinter100dedos",
    "delegated_hp": 0,
    "total_account_hp": 285.3579748057419,
    "last_user_post": "2024-01-27T06:04:51",
    "token_balance": 0,
    "timestamp": null,
    "last_vote_date": null,
    "votes_month": 0,
    "in_curation_trail": false
  },
  {
    "delegator": "surfgurupro",
    "delegated_hp": 0,
    "total_account_hp": 70.31082014936636,
    "last_user_post": "2025-08-14T20:42:57",
    "token_balance": 0,
    "timestamp": null,
    "last_vote_date": null,
    "votes_month": 0,
    "in_curation_trail": false
  },
  {
    "delegator": "surflimpo",
    "delegated_hp": 0,
    "total_account_hp": 155.34858518209194,
    "last_user_post": "2024-04-19T21:23:06",
    "token_balance": 0,
    "timestamp": null,
    "last_vote_date": null,
    "votes_month": 0,
    "in_curation_trail": false
  },
  {
    "delegator": "tankulo",
    "delegated_hp": 0,
    "total_account_hp": 0,
    "last_user_post": "2024-08-25T06:47:57",
    "token_balance": 0,
    "timestamp": null,
    "last_vote_date": null,
    "votes_month": 0,
    "in_curation_trail": false
  },
  {
    "delegator": "tatianest",
    "delegated_hp": 0,
    "total_account_hp": 0.21785323889630936,
    "last_user_post": "2024-02-28T20:56:54",
    "token_balance": 0,
    "timestamp": null,
    "last_vote_date": null,
    "votes_month": 0,
    "in_curation_trail": false
  },
  {
    "delegator": "tatylayla",
    "delegated_hp": 0,
    "total_account_hp": 91.91895955985969,
    "last_user_post": "2020-03-03T22:06:39",
    "token_balance": 0,
    "timestamp": null,
    "last_vote_date": null,
    "votes_month": 0,
    "in_curation_trail": false
  },
  {
    "delegator": "teteuzinho",
    "delegated_hp": 0,
    "total_account_hp": 1.2474365482951313,
    "last_user_post": "2023-05-16T01:46:33",
    "token_balance": 0,
    "timestamp": null,
    "last_vote_date": null,
    "votes_month": 0,
    "in_curation_trail": false
  },
  {
    "delegator": "teu",
    "delegated_hp": 0,
    "total_account_hp": 9.718307121923248,
    "last_user_post": "2024-02-23T20:09:03",
    "token_balance": 0,
    "timestamp": null,
    "last_vote_date": null,
    "votes_month": 0,
    "in_curation_trail": false
  },
  {
    "delegator": "thaliaperez",
    "delegated_hp": 0,
    "total_account_hp": 45.68107602658733,
    "last_user_post": "2025-10-14T09:55:15",
    "token_balance": 0,
    "timestamp": null,
    "last_vote_date": null,
    "votes_month": 0,
    "in_curation_trail": false
  },
  {
    "delegator": "totomusic",
    "delegated_hp": 0,
    "total_account_hp": 0,
    "last_user_post": "2025-11-22T16:33:12",
    "token_balance": 0,
    "timestamp": null,
    "last_vote_date": null,
    "votes_month": 0,
    "in_curation_trail": false
  },
  {
    "delegator": "triptamine555",
    "delegated_hp": 0,
    "total_account_hp": 0,
    "last_user_post": "2024-05-28T00:26:54",
    "token_balance": 0,
    "timestamp": null,
    "last_vote_date": null,
    "votes_month": 0,
    "in_curation_trail": false
  },
  {
    "delegator": "tucacheias",
    "delegated_hp": 0,
    "total_account_hp": 9.807868615738153,
    "last_user_post": "2024-04-10T18:30:21",
    "token_balance": 0,
    "timestamp": null,
    "last_vote_date": null,
    "votes_month": 0,
    "in_curation_trail": false
  },
  {
    "delegator": "ukyron3",
    "delegated_hp": 0,
    "total_account_hp": 0.0005995247548767677,
    "last_user_post": "2025-02-12T22:06:18",
    "token_balance": 0,
    "timestamp": null,
    "last_vote_date": null,
    "votes_month": 0,
    "in_curation_trail": false
  },
  {
    "delegator": "unhurried",
    "delegated_hp": 0,
    "total_account_hp": 146.90890328764652,
    "last_user_post": "2022-11-08T16:25:30",
    "token_balance": 0,
    "timestamp": null,
    "last_vote_date": null,
    "votes_month": 0,
    "in_curation_trail": false
  },
  {
    "delegator": "unten1995",
    "delegated_hp": 0,
    "total_account_hp": 0,
    "last_user_post": "2024-03-29T00:52:21",
    "token_balance": 0,
    "timestamp": null,
    "last_vote_date": null,
    "votes_month": 0,
    "in_curation_trail": false
  },
  {
    "delegator": "usergabs",
    "delegated_hp": 0,
    "total_account_hp": 5.488339487532814,
    "last_user_post": "2024-05-14T18:48:18",
    "token_balance": 0,
    "timestamp": null,
    "last_vote_date": null,
    "votes_month": 0,
    "in_curation_trail": false
  },
  {
    "delegator": "vaipraonde",
    "delegated_hp": 0,
    "total_account_hp": 4794.904313565111,
    "last_user_post": "2025-12-17T00:27:12",
    "token_balance": 65.03256277,
    "timestamp": null,
    "last_vote_date": "2025-10-25T21:54:21",
    "votes_month": 0,
    "in_curation_trail": false
  },
  {
    "delegator": "vanessabarrostec",
    "delegated_hp": 0,
    "total_account_hp": 6.687503671455863,
    "last_user_post": "2024-08-16T13:01:36",
    "token_balance": 0,
    "timestamp": null,
    "last_vote_date": null,
    "votes_month": 0,
    "in_curation_trail": false
  },
  {
    "delegator": "vcorioh",
    "delegated_hp": 0,
    "total_account_hp": 2.751241284616472,
    "last_user_post": "2021-08-10T15:15:42",
    "token_balance": 0,
    "timestamp": null,
    "last_vote_date": null,
    "votes_month": 0,
    "in_curation_trail": false
  },
  {
    "delegator": "vempromundo",
    "delegated_hp": 0,
    "total_account_hp": 8695.390844360534,
    "last_user_post": "2025-12-17T08:26:51",
    "token_balance": 200,
    "timestamp": null,
    "last_vote_date": "2025-12-16T14:35:30",
    "votes_month": 4,
    "in_curation_trail": true
  },
  {
    "delegator": "ventrinidad",
    "delegated_hp": 0,
    "total_account_hp": 16.578538703139543,
    "last_user_post": "2024-06-19T15:13:45",
    "token_balance": 0,
    "timestamp": null,
    "last_vote_date": null,
    "votes_month": 0,
    "in_curation_trail": false
  },
  {
    "delegator": "vicvondoom",
    "delegated_hp": 0,
    "total_account_hp": 0.0012304455084518138,
    "last_user_post": "2024-07-31T16:16:57",
    "token_balance": 0,
    "timestamp": null,
    "last_vote_date": null,
    "votes_month": 0,
    "in_curation_trail": false
  },
  {
    "delegator": "vini0",
    "delegated_hp": 0,
    "total_account_hp": 0.0007114644753726172,
    "last_user_post": "2024-11-26T22:47:09",
    "token_balance": 0,
    "timestamp": null,
    "last_vote_date": null,
    "votes_month": 0,
    "in_curation_trail": false
  },
  {
    "delegator": "vitoragnelli",
    "delegated_hp": 0,
    "total_account_hp": 23.461144499052207,
    "last_user_post": "2022-05-30T03:30:15",
    "token_balance": 0,
    "timestamp": null,
    "last_vote_date": null,
    "votes_month": 0,
    "in_curation_trail": false
  },
  {
    "delegator": "vonlecram",
    "delegated_hp": 0,
    "total_account_hp": 79.38207620544162,
    "last_user_post": "2025-09-28T21:26:36",
    "token_balance": 0,
    "timestamp": null,
    "last_vote_date": null,
    "votes_month": 0,
    "in_curation_trail": false
  },
  {
    "delegator": "wallabra",
    "delegated_hp": 0,
    "total_account_hp": 0,
    "last_user_post": "2024-04-10T13:59:39",
    "token_balance": 0,
    "timestamp": null,
    "last_vote_date": null,
    "votes_month": 0,
    "in_curation_trail": false
  },
  {
    "delegator": "wallabra-wallet",
    "delegated_hp": 0,
    "total_account_hp": 2.3644308402174694,
    "last_user_post": "2025-10-04T20:30:12",
    "token_balance": 0,
    "timestamp": null,
    "last_vote_date": null,
    "votes_month": 0,
    "in_curation_trail": false
  },
  {
    "delegator": "wasye",
    "delegated_hp": 0,
    "total_account_hp": 138.36990280520004,
    "last_user_post": "2025-07-15T21:13:48",
    "token_balance": 0,
    "timestamp": null,
    "last_vote_date": null,
    "votes_month": 0,
    "in_curation_trail": false
  },
  {
    "delegator": "wellingt556",
    "delegated_hp": 0,
    "total_account_hp": 2.169751468753964,
    "last_user_post": "2024-10-27T12:48:57",
    "token_balance": 0,
    "timestamp": null,
    "last_vote_date": null,
    "votes_month": 0,
    "in_curation_trail": false
  },
  {
    "delegator": "wilkersk8zn",
    "delegated_hp": 0,
    "total_account_hp": 0,
    "last_user_post": "2024-08-04T17:43:03",
    "token_balance": 0,
    "timestamp": null,
    "last_vote_date": null,
    "votes_month": 0,
    "in_curation_trail": false
  },
  {
    "delegator": "wlfreitas",
    "delegated_hp": 0,
    "total_account_hp": 12.637342543309119,
    "last_user_post": "2025-09-26T20:11:12",
    "token_balance": 0,
    "timestamp": null,
    "last_vote_date": null,
    "votes_month": 0,
    "in_curation_trail": true
  },
  {
    "delegator": "xgoivo",
    "delegated_hp": 0,
    "total_account_hp": 33.528723361364655,
    "last_user_post": "2022-04-10T15:57:45",
    "token_balance": 0,
    "timestamp": null,
    "last_vote_date": null,
    "votes_month": 0,
    "in_curation_trail": false
  },
  {
    "delegator": "xlety",
    "delegated_hp": 0,
    "total_account_hp": 3936.887312141109,
    "last_user_post": "2025-11-25T21:47:12",
    "token_balance": 51.43796971,
    "timestamp": null,
    "last_vote_date": "2025-11-25T21:48:24",
    "votes_month": 4,
    "in_curation_trail": true
  },
  {
    "delegator": "xtryhard",
    "delegated_hp": 0,
    "total_account_hp": 0.0014688776664432206,
    "last_user_post": "2022-03-25T14:22:48",
    "token_balance": 0,
    "timestamp": null,
    "last_vote_date": null,
    "votes_month": 0,
    "in_curation_trail": false
  },
  {
    "delegator": "yungbresciani",
    "delegated_hp": 0,
    "total_account_hp": 339.72468210523454,
    "last_user_post": "2025-12-16T18:20:06",
    "token_balance": 0,
    "timestamp": null,
    "last_vote_date": null,
    "votes_month": 0,
    "in_curation_trail": false
  },
  {
    "delegator": "zallin",
    "delegated_hp": 0,
    "total_account_hp": 3545.6469609113783,
    "last_user_post": "2025-07-11T13:09:12",
    "token_balance": 60.546,
    "timestamp": null,
    "last_vote_date": null,
    "votes_month": 0,
    "in_curation_trail": true
  }
]