{
  "last_updated": "2026-01-10T18:52:09.784Z",
  "total_delegators": 65,
  "total_hp": 41390.74699999999,
  "project_account_hp": 14277.479937532002,
  "total_hbr_staked": 5325.0395579900005,
  "curation_trail_count": 85,
  "active_community_members": 314,
  "active_brazilians": 24,
  "votes_24h": 16,
  "vote_history_named": {
    "Janeiro 2026": 118,
    "Dezembro 2025": 351,
    "Novembro 2025": 405,
    "Outubro 2025": 266
  },
  "votes_month_current": 118,
  "votes_month_prev1": 351,
  "votes_month_prev2": 405
}